osrs_python_bot/__init__.py
osrs_python_bot/src/__init__.py
osrs_python_bot/src/bots/__init__.py
osrs_python_bot/src/bots/combat.py
osrs_python_bot/src/bots/herblore.py
osrs_python_bot/src/bots/magic.py
osrs_python_bot/src/common/__init__.py
osrs_python_bot/src/common/bank_manager.py
osrs_python_bot/src/common/inventory_clicker.py
osrs_python_bot-0.2.1.dist-info/LICENSE
osrs_python_bot-0.2.1.dist-info/METADATA
osrs_python_bot-0.2.1.dist-info/WHEEL
osrs_python_bot-0.2.1.dist-info/top_level.txt
osrs_python_bot-0.2.1.dist-info/RECORD
