Metadata-Version: 2.1
Name: osrs-python-bot
Version: 0.2.1
Home-page: https://github.com/osrs-bots/osrs-python-bot
Author: osrs-bots
Author-email: 
Keywords: osrs-bots
Classifier: Intended Audience :: Developers
Classifier: Programming Language :: Python :: 3
Classifier: Operating System :: Microsoft :: Windows
License-File: LICENSE
Requires-Dist: pyautogui
Requires-Dist: pynput
